anylink/__init__.py
anylink/admin.py
anylink/apps.py
anylink/extensions.py
anylink/fields.py
anylink/forms.py
anylink/models.py
anylink/widgets.py
anylink/locale/de/LC_MESSAGES/django.mo
anylink/locale/de/LC_MESSAGES/django.po
anylink/locale/nl/LC_MESSAGES/django.mo
anylink/locale/nl/LC_MESSAGES/django.po
anylink/static/anylink/anylink-addorchangewidget.js
anylink/static/tiny_mce/plugins/anylink/editor_plugin.js
anylink/static/tiny_mce/plugins/anylink/img/link.gif
anylink/static/tiny_mce/plugins/anylink/langs/de.js
anylink/static/tiny_mce/plugins/anylink/langs/de_dlg.js
anylink/static/tiny_mce/plugins/anylink/langs/en.js
anylink/static/tiny_mce/plugins/anylink/langs/en_dlg.js
anylink/templates/admin/anylink/anylink/addorchange_response.html
anylink/templates/admin/anylink/anylink/change_form.html
anylink/templates/admin/anylink/anylink/change_list.html
anylink/templates/admin/anylink/anylink/rtelink_response.html
anylink/templatetags/__init__.py
anylink/templatetags/anylink_tags.py
django_anylink-2.0.1.dist-info/LICENSE
django_anylink-2.0.1.dist-info/METADATA
django_anylink-2.0.1.dist-info/WHEEL
django_anylink-2.0.1.dist-info/top_level.txt
django_anylink-2.0.1.dist-info/RECORD
