Metadata-Version: 2.1
Name: django-anylink
Version: 2.0.1
Summary: Generic links for Django models.
Home-page: https://github.com/moccu/django-anylink/
Author: Moccu GmbH & Co. KG
Author-email: info@moccu.com
License: UNKNOWN
Platform: UNKNOWN
Classifier: Development Status :: 4 - Beta
Classifier: Environment :: Web Environment
Classifier: Intended Audience :: Developers
Classifier: License :: OSI Approved :: BSD License
Classifier: Operating System :: OS Independent
Classifier: Programming Language :: Python
Classifier: Programming Language :: Python :: 3
Classifier: Programming Language :: Python :: 3.6
Classifier: Programming Language :: Python :: 3.7
Classifier: Programming Language :: Python :: 3.8
Classifier: Programming Language :: Python :: Implementation :: CPython
Classifier: Framework :: Django
License-File: LICENSE
Requires-Dist: Django (<4)
Provides-Extra: docs
Requires-Dist: sphinx ; extra == 'docs'
Requires-Dist: sphinx-rtd-theme ; extra == 'docs'
Provides-Extra: tests
Requires-Dist: pytest ; extra == 'tests'
Requires-Dist: pytest-cache ; extra == 'tests'
Requires-Dist: pytest-cov ; extra == 'tests'
Requires-Dist: pytest-flakes ; extra == 'tests'
Requires-Dist: pytest-pycodestyle ; extra == 'tests'
Requires-Dist: pytest-isort ; extra == 'tests'
Requires-Dist: pytest-django ; extra == 'tests'
Requires-Dist: coverage ; extra == 'tests'
Requires-Dist: tox ; extra == 'tests'
